setup.cfg
setup.py
pysteam/__init__.py
pysteam/_crc_algorithms.py
pysteam/_shortcut_generator.py
pysteam/_shortcut_parser.py
pysteam/communityids.py
pysteam/grid.py
pysteam/model.py
pysteam/paths.py
pysteam/shortcuts.py
pysteam/steam.py
pysteam/winutils.py
pysteam_steamos.egg-info/PKG-INFO
pysteam_steamos.egg-info/SOURCES.txt
pysteam_steamos.egg-info/dependency_links.txt
pysteam_steamos.egg-info/not-zip-safe
pysteam_steamos.egg-info/top_level.txt