Metadata-Version: 1.0
Name: pysteam-steamos
Version: 1.0.2-b2
Summary: Python library to work with Steam. For SteamOS. Corrects naming convention.
Home-page: http://github.com/scottrice/pysteam
Author: Michael DeGuzis, Scott Rice
Author-email: UNKNOWN
License: MIT
Platform: UNKNOWN
